discord_hero_scheduler-0.1.0b0.dist-info/METADATA
discord_hero_scheduler-0.1.0b0.dist-info/RECORD
discord_hero_scheduler-0.1.0b0.dist-info/WHEEL
discord_hero_scheduler-0.1.0b0.dist-info/top_level.txt
hero/extensions/scheduler/__init__.py
hero/extensions/scheduler/cogs.py
hero/extensions/scheduler/controller.py
hero/extensions/scheduler/fields.py
hero/extensions/scheduler/models.py
